LICENSE
MANIFEST.in
README.md
requirements.txt
setup.cfg
setup.py
attributes/__init__.py
attributes/actions.py
attributes/constants.py
attributes/fields.py
attributes/forms.py
attributes/managers.py
attributes/querysets.py
attributes/translation.py
attributes/utils.py
attributes/widgets.py
attributes/admin/__init__.py
attributes/admin/forms.py
attributes/locale/ru/LC_MESSAGES/django.mo
attributes/locale/ru/LC_MESSAGES/django.po
attributes/locale/uk/LC_MESSAGES/django.mo
attributes/locale/uk/LC_MESSAGES/django.po
attributes/migrations/0001_initial.py
attributes/migrations/0002_translate_field.py
attributes/migrations/__init__.py
attributes/models/__init__.py
attributes/models/attribute.py
attributes/models/attribute_option.py
attributes/models/attribute_value.py
attributes/static/attrs/form.js
attributes/templates/attributes-form.html
attributes/templates/change-attr-category-action.html
django_mp_attributes.egg-info/PKG-INFO
django_mp_attributes.egg-info/SOURCES.txt
django_mp_attributes.egg-info/dependency_links.txt
django_mp_attributes.egg-info/requires.txt
django_mp_attributes.egg-info/top_level.txt