Metadata-Version: 1.1
Name: django-mp-attributes
Version: 1.1.3
Summary: Django attributes app
Home-page: https://github.com/pmaigutyak/mp-attributes
Author: Paul Maigutyak
Author-email: pmaigutyak@gmail.com
License: MIT
Download-URL: https://github.com/pmaigutyak/mp-attributes/archive/1.1.3.tar.gz
Platform: UNKNOWN
